whitebox_plugin_leaflet/pyproject.toml
whitebox_plugin_leaflet/__init__.py
whitebox_plugin_leaflet/external-asset-manifest.json
whitebox_plugin_leaflet/whitebox_plugin_leaflet.py
whitebox_test_plugin_leaflet/__init__.py
whitebox_test_plugin_leaflet/test_whitebox_plugin_leaflet.py
whitebox_plugin_leaflet-0.1.3.dist-info/LICENSE
whitebox_plugin_leaflet-0.1.3.dist-info/METADATA
whitebox_plugin_leaflet-0.1.3.dist-info/WHEEL
whitebox_plugin_leaflet-0.1.3.dist-info/RECORD
